yolo_formatter/__init__.py
yolo_formatter/yolo_dataset_formatter.py
yolo_formatter-0.2.dist-info/LICENSE
yolo_formatter-0.2.dist-info/METADATA
yolo_formatter-0.2.dist-info/WHEEL
yolo_formatter-0.2.dist-info/top_level.txt
yolo_formatter-0.2.dist-info/RECORD
