Metadata-Version: 2.1
Name: yolo_formatter
Version: 0.2
Summary: A Python package to create a proper structured dataset that YOLO understands.
Home-page: https://github.com/yourusername/yolo_formatter
Author: Your Name
Author-email: your_email@example.com
Classifier: Programming Language :: Python :: 3
Classifier: License :: OSI Approved :: MIT License
Classifier: Operating System :: OS Independent
Requires-Python: >=3.6
License-File: LICENSE
Requires-Dist: scikit-learn
